README.md
setup.cfg
setup.py
spikesorting_tsne/__init__.py
spikesorting_tsne/constants.py
spikesorting_tsne/gpu.py
spikesorting_tsne/io_with_cpp.py
spikesorting_tsne/preprocessing_kilosort_results.py
spikesorting_tsne/spike_positioning_on_probe.py
spikesorting_tsne/stopwatch.py
spikesorting_tsne/tsne.py
spikesorting_tsne/visualization.py
spikesorting_tsne.egg-info/PKG-INFO
spikesorting_tsne.egg-info/SOURCES.txt
spikesorting_tsne.egg-info/dependency_links.txt
spikesorting_tsne.egg-info/not-zip-safe
spikesorting_tsne.egg-info/top_level.txt