Metadata-Version: 2.1
Name: spikesorting-tsne
Version: 1.0.10
Summary: T-sne with burnes hut and cuda extension (with python wrappers and python code for spike sorting)
Home-page: https://github.com/georgedimitriadis/spikesorting_tsne
Author: George Dimitriadis
Author-email: gdimitri@hotmail.com
License: UNKNOWN
Project-URL: Documentation, https://georgedimitriadis.github.io/spikesorting_tsne/
Project-URL: Python code repository, https://github.com/georgedimitriadis/spikesorting_tsne
Project-URL: C++ code repository, https://github.com/georgedimitriadis/spikesorting_tsne_bhpart
Platform: UNKNOWN
Classifier: Development Status :: 5 - Production/Stable
Classifier: Intended Audience :: Science/Research
Classifier: Operating System :: Microsoft :: Windows
Classifier: Operating System :: POSIX :: Linux
Classifier: Topic :: Scientific/Engineering :: Visualization
Classifier: License :: OSI Approved :: MIT License
Classifier: Programming Language :: Python :: 3.5
Classifier: Programming Language :: Python :: 3.6
Requires-Python: >=3.5
